euler/__init__.py
euler/euler.py
eulerdg-0.0.3.dist-info/LICENSE.md
eulerdg-0.0.3.dist-info/METADATA
eulerdg-0.0.3.dist-info/WHEEL
eulerdg-0.0.3.dist-info/top_level.txt
eulerdg-0.0.3.dist-info/RECORD
